zibuyu_evernote/__init__.py
zibuyu_evernote/api/__init__.py
zibuyu_evernote/api/apis.py
zibuyu_evernote/api/client.py
zibuyu_evernote/api/converter.py
zibuyu_evernote/api/ttypes.py
zibuyu_evernote/edam/__init__.py
zibuyu_evernote/edam/error/__init__.py
zibuyu_evernote/edam/error/constants.py
zibuyu_evernote/edam/error/ttypes.py
zibuyu_evernote/edam/limits/__init__.py
zibuyu_evernote/edam/limits/constants.py
zibuyu_evernote/edam/limits/ttypes.py
zibuyu_evernote/edam/notestore/NoteStore.py
zibuyu_evernote/edam/notestore/__init__.py
zibuyu_evernote/edam/notestore/constants.py
zibuyu_evernote/edam/notestore/ttypes.py
zibuyu_evernote/edam/type/__init__.py
zibuyu_evernote/edam/type/constants.py
zibuyu_evernote/edam/type/ttypes.py
zibuyu_evernote/edam/userstore/UserStore.py
zibuyu_evernote/edam/userstore/__init__.py
zibuyu_evernote/edam/userstore/constants.py
zibuyu_evernote/edam/userstore/ttypes.py
zibuyu_evernote/thrift/TSCons.py
zibuyu_evernote/thrift/TSerialization.py
zibuyu_evernote/thrift/Thrift.py
zibuyu_evernote/thrift/__init__.py
zibuyu_evernote/thrift/protocol/TBase.py
zibuyu_evernote/thrift/protocol/TBinaryProtocol.py
zibuyu_evernote/thrift/protocol/TProtocol.py
zibuyu_evernote/thrift/protocol/__init__.py
zibuyu_evernote/thrift/transport/THttpClient.py
zibuyu_evernote/thrift/transport/TTransport.py
zibuyu_evernote/thrift/transport/TTwisted.py
zibuyu_evernote/thrift/transport/__init__.py
zibuyu_evernote-0.0.3.dist-info/LICENSE
zibuyu_evernote-0.0.3.dist-info/METADATA
zibuyu_evernote-0.0.3.dist-info/WHEEL
zibuyu_evernote-0.0.3.dist-info/top_level.txt
zibuyu_evernote-0.0.3.dist-info/RECORD
