Metadata-Version: 2.2
Name: zibuyu_evernote
Version: 0.0.3
Summary: 子不语个人工具包-印象笔记SDK
Home-page: https://github.com/zibuyu2015831/zibuyu_evernote
Author: 子不语
License: MIT
Keywords: zibuyu,zibuyu_evernote,evernote
Classifier: License :: OSI Approved :: MIT License
Classifier: Operating System :: OS Independent
Classifier: Intended Audience :: Developers
Classifier: Programming Language :: Python :: 3.9
Classifier: Programming Language :: Python :: 3.10
Classifier: Programming Language :: Python :: 3.11
Classifier: Programming Language :: Python :: 3.12
Requires-Python: >=3.9
License-File: LICENSE
Requires-Dist: certifi
Requires-Dist: charset-normalizer
Requires-Dist: html2text
Requires-Dist: httplib2
Requires-Dist: idna
Requires-Dist: Markdown
Requires-Dist: oauth2
Requires-Dist: oauthlib
Requires-Dist: pip
Requires-Dist: Pygments
Requires-Dist: pyparsing
Requires-Dist: requests
Requires-Dist: requests-oauthlib
Requires-Dist: setuptools
Requires-Dist: urllib3
Requires-Dist: wheel
Dynamic: author
Dynamic: classifier
Dynamic: description
Dynamic: description-content-type
Dynamic: home-page
Dynamic: keywords
Dynamic: license
Dynamic: requires-dist
Dynamic: requires-python
Dynamic: summary
